fh_dev_utils/__init__.py
fh_dev_utils/_modidx.py
fh_dev_utils/serve.py
fh_dev_utils-0.0.4.dist-info/LICENSE
fh_dev_utils-0.0.4.dist-info/METADATA
fh_dev_utils-0.0.4.dist-info/WHEEL
fh_dev_utils-0.0.4.dist-info/entry_points.txt
fh_dev_utils-0.0.4.dist-info/top_level.txt
fh_dev_utils-0.0.4.dist-info/RECORD
