Metadata-Version: 2.1
Name: fh-dev-utils
Version: 0.0.4
Summary: Utility functions to help with the development of FastHTML applications.
Home-page: https://github.com/ExploringML/fh-dev-utils
Author: David Gwyer
Author-email: d.v.gwyer@gmail.com
License: Apache Software License 2.0
Keywords: nbdev jupyter notebook python
Classifier: Development Status :: 4 - Beta
Classifier: Intended Audience :: Developers
Classifier: Natural Language :: English
Classifier: Programming Language :: Python :: 3.7
Classifier: Programming Language :: Python :: 3.8
Classifier: Programming Language :: Python :: 3.9
Classifier: Programming Language :: Python :: 3.10
Classifier: Programming Language :: Python :: 3.11
Classifier: Programming Language :: Python :: 3.12
Classifier: License :: OSI Approved :: Apache Software License
Requires-Python: >=3.7
License-File: LICENSE
Requires-Dist: python-fasthtml
Requires-Dist: pytailwindcss
Requires-Dist: jupyterlab
Requires-Dist: sqlite-web
Provides-Extra: dev
